{
  "resourceType": "ClinicalUseDefinition",
  "id": "cytarabine-acute-myeloblastic-leukemia-with-maturation",
  "meta": {
    "profile": [
      "https://phtxgnn.github.io/fhir/StructureDefinition/phtxgnn-indication"
    ]
  },
  "type": "indication",
  "status": "active",
  "subject": [
    {
      "reference": "MedicationKnowledge/cytarabine"
    }
  ],
  "indication": {
    "diseaseSymptomProcedure": {
      "concept": {
        "coding": [
          {
            "system": "http://snomed.info/sct",
            "display": "acute myeloblastic leukemia with maturation"
          }
        ],
        "text": "acute myeloblastic leukemia with maturation"
      }
    }
  },
  "extension": [
    {
      "url": "https://phtxgnn.github.io/fhir/StructureDefinition/evidence-level",
      "valueCode": "L5"
    },
    {
      "url": "https://phtxgnn.github.io/fhir/StructureDefinition/prediction-source",
      "valueString": "TxGNN Knowledge Graph"
    }
  ]
}