{
  "resourceType": "MedicationKnowledge",
  "id": "methylene-blue",
  "meta": {
    "profile": [
      "https://phtxgnn.github.io/fhir/StructureDefinition/phtxgnn-medication"
    ]
  },
  "status": "active",
  "code": {
    "coding": [
      {
        "system": "https://www.drugbank.ca/drugs",
        "code": "DB09241",
        "display": "METHYLENE BLUE"
      },
      {
        "system": "https://phtxgnn.github.io/drugs",
        "code": "methylene-blue",
        "display": "METHYLENE BLUE"
      }
    ],
    "text": "METHYLENE BLUE"
  },
  "intendedJurisdiction": [
    {
      "coding": [
        {
          "system": "urn:iso:std:iso:3166",
          "code": "PH",
          "display": "Philippines"
        }
      ]
    }
  ],
  "extension": [
    {
      "url": "https://phtxgnn.github.io/fhir/StructureDefinition/evidence-level",
      "valueCode": "L5"
    }
  ]
}